{"4477999000JJJQQQKKAA":{"cardType":11,"cardLength":4,"maxPokeValue":12,"minPokeValue":9,"cardValue":54},"5577999000JJJQQQKKAA":{"cardType":11,"cardLength":4,"maxPokeValue":12,"minPokeValue":9,"cardValue":54},"6677999000JJJQQQKKAA":{"cardType":11,"cardLength":4,"maxPokeValue":12,"minPokeValue":9,"cardValue":54},"3388999000JJJQQQKKAA":{"cardType":11,"cardLength":4,"maxPokeValue":12,"minPokeValue":9,"cardValue":54},"4488999000JJJQQQKKAA":{"cardType":11,"cardLength":4,"maxPokeValue":12,"minPokeValue":9,"cardValue":54},"5588999000JJJQQQKKAA":{"cardType":11,"cardLength":4,"maxPokeValue":12,"minPokeValue":9,"cardValue":54},"6688999000JJJQQQKKAA":{"cardType":11,"cardLength":4,"maxPokeValue":12,"minPokeValue":9,"cardValue":54},"7788999000JJJQQQKKAA":{"cardType":11,"cardLength":4,"maxPokeValue":12,"minPokeValue":9,"cardValue":54},"334455999000JJJQQQ22":{"cardType":11,"cardLength":4,"maxPokeValue":12,"minPokeValue":9,"cardValue":54},"334466999000JJJQQQ22":{"cardType":11,"cardLength":4,"maxPokeValue":12,"minPokeValue":9,"cardValue":54},"335566999000JJJQQQ22":{"cardType":11,"cardLength":4,"maxPokeValue":12,"minPokeValue":9,"cardValue":54},"445566999000JJJQQQ22":{"cardType":11,"cardLength":4,"maxPokeValue":12,"minPokeValue":9,"cardValue":54},"334477999000JJJQQQ22":{"cardType":11,"cardLength":4,"maxPokeValue":12,"minPokeValue":9,"cardValue":54},"335577999000JJJQQQ22":{"cardType":11,"cardLength":4,"maxPokeValue":12,"minPokeValue":9,"cardValue":54},"445577999000JJJQQQ22":{"cardType":11,"cardLength":4,"maxPokeValue":12,"minPokeValue":9,"cardValue":54},"336677999000JJJQQQ22":{"cardType":11,"cardLength":4,"maxPokeValue":12,"minPokeValue":9,"cardValue":54},"446677999000JJJQQQ22":{"cardType":11,"cardLength":4,"maxPokeValue":12,"minPokeValue":9,"cardValue":54},"556677999000JJJQQQ22":{"cardType":11,"cardLength":4,"maxPokeValue":12,"minPokeValue":9,"cardValue":54},"334488999000JJJQQQ22":{"cardType":11,"cardLength":4,"maxPokeValue":12,"minPokeValue":9,"cardValue":54},"335588999000JJJQQQ22":{"cardType":11,"cardLength":4,"maxPokeValue":12,"minPokeValue":9,"cardValue":54},"445588999000JJJQQQ22":{"cardType":11,"cardLength":4,"maxPokeValue":12,"minPokeValue":9,"cardValue":54},"336688999000JJJQQQ22":{"cardType":11,"cardLength":4,"maxPokeValue":12,"minPokeValue":9,"cardValue":54},"446688999000JJJQQQ22":{"cardType":11,"cardLength":4,"maxPokeValue":12,"minPokeValue":9,"cardValue":54},"556688999000JJJQQQ22":{"cardType":11,"cardLength":4,"maxPokeValue":12,"minPokeValue":9,"cardValue":54},"337788999000JJJQQQ22":{"cardType":11,"cardLength":4,"maxPokeValue":12,"minPokeValue":9,"cardValue":54},"447788999000JJJQQQ22":{"cardType":11,"cardLength":4,"maxPokeValue":12,"minPokeValue":9,"cardValue":54},"557788999000JJJQQQ22":{"cardType":11,"cardLength":4,"maxPokeValue":12,"minPokeValue":9,"cardValue":54},"667788999000JJJQQQ22":{"cardType":11,"cardLength":4,"maxPokeValue":12,"minPokeValue":9,"cardValue":54},"3344999000JJJQQQKK22":{"cardType":11,"cardLength":4,"maxPokeValue":12,"minPokeValue":9,"cardValue":54},"3355999000JJJQQQKK22":{"cardType":11,"cardLength":4,"maxPokeValue":12,"minPokeValue":9,"cardValue":54},"4455999000JJJQQQKK22":{"cardType":11,"cardLength":4,"maxPokeValue":12,"minPokeValue":9,"cardValue":54},"3366999000JJJQQQKK22":{"cardType":11,"cardLength":4,"maxPokeValue":12,"minPokeValue":9,"cardValue":54},"4466999000JJJQQQKK22":{"cardType":11,"cardLength":4,"maxPokeValue":12,"minPokeValue":9,"cardValue":54},"5566999000JJJQQQKK22":{"cardType":11,"cardLength":4,"maxPokeValue":12,"minPokeValue":9,"cardValue":54},"3377999000JJJQQQKK22":{"cardType":11,"cardLength":4,"maxPokeValue":12,"minPokeValue":9,"cardValue":54},"4477999000JJJQQQKK22":{"cardType":11,"cardLength":4,"maxPokeValue":12,"minPokeValue":9,"cardValue":54},"5577999000JJJQQQKK22":{"cardType":11,"cardLength":4,"maxPokeValue":12,"minPokeValue":9,"cardValue":54},"6677999000JJJQQQKK22":{"cardType":11,"cardLength":4,"maxPokeValue":12,"minPokeValue":9,"cardValue":54},"3388999000JJJQQQKK22":{"cardType":11,"cardLength":4,"maxPokeValue":12,"minPokeValue":9,"cardValue":54},"4488999000JJJQQQKK22":{"cardType":11,"cardLength":4,"maxPokeValue":12,"minPokeValue":9,"cardValue":54},"5588999000JJJQQQKK22":{"cardType":11,"cardLength":4,"maxPokeValue":12,"minPokeValue":9,"cardValue":54},"6688999000JJJQQQKK22":{"cardType":11,"cardLength":4,"maxPokeValue":12,"minPokeValue":9,"cardValue":54},"7788999000JJJQQQKK22":{"cardType":11,"cardLength":4,"maxPokeValue":12,"minPokeValue":9,"cardValue":54},"3344999000JJJQQQAA22":{"cardType":11,"cardLength":4,"maxPokeValue":12,"minPokeValue":9,"cardValue":54},"3355999000JJJQQQAA22":{"cardType":11,"cardLength":4,"maxPokeValue":12,"minPokeValue":9,"cardValue":54},"4455999000JJJQQQAA22":{"cardType":11,"cardLength":4,"maxPokeValue":12,"minPokeValue":9,"cardValue":54},"3366999000JJJQQQAA22":{"cardType":11,"cardLength":4,"maxPokeValue":12,"minPokeValue":9,"cardValue":54},"4466999000JJJQQQAA22":{"cardType":11,"cardLength":4,"maxPokeValue":12,"minPokeValue":9,"cardValue":54},"5566999000JJJQQQAA22":{"cardType":11,"cardLength":4,"maxPokeValue":12,"minPokeValue":9,"cardValue":54},"3377999000JJJQQQAA22":{"cardType":11,"cardLength":4,"maxPokeValue":12,"minPokeValue":9,"cardValue":54},"4477999000JJJQQQAA22":{"cardType":11,"cardLength":4,"maxPokeValue":12,"minPokeValue":9,"cardValue":54},"5577999000JJJQQQAA22":{"cardType":11,"cardLength":4,"maxPokeValue":12,"minPokeValue":9,"cardValue":54},"6677999000JJJQQQAA22":{"cardType":11,"cardLength":4,"maxPokeValue":12,"minPokeValue":9,"cardValue":54},"3388999000JJJQQQAA22":{"cardType":11,"cardLength":4,"maxPokeValue":12,"minPokeValue":9,"cardValue":54},"4488999000JJJQQQAA22":{"cardType":11,"cardLength":4,"maxPokeValue":12,"minPokeValue":9,"cardValue":54},"5588999000JJJQQQAA22":{"cardType":11,"cardLength":4,"maxPokeValue":12,"minPokeValue":9,"cardValue":54},"6688999000JJJQQQAA22":{"cardType":11,"cardLength":4,"maxPokeValue":12,"minPokeValue":9,"cardValue":54},"7788999000JJJQQQAA22":{"cardType":11,"cardLength":4,"maxPokeValue":12,"minPokeValue":9,"cardValue":54},"33999000JJJQQQKKAA22":{"cardType":11,"cardLength":4,"maxPokeValue":12,"minPokeValue":9,"cardValue":54},"44999000JJJQQQKKAA22":{"cardType":11,"cardLength":4,"maxPokeValue":12,"minPokeValue":9,"cardValue":54},"55999000JJJQQQKKAA22":{"cardType":11,"cardLength":4,"maxPokeValue":12,"minPokeValue":9,"cardValue":54},"66999000JJJQQQKKAA22":{"cardType":11,"cardLength":4,"maxPokeValue":12,"minPokeValue":9,"cardValue":54},"77999000JJJQQQKKAA22":{"cardType":11,"cardLength":4,"maxPokeValue":12,"minPokeValue":9,"cardValue":54},"88999000JJJQQQKKAA22":{"cardType":11,"cardLength":4,"maxPokeValue":12,"minPokeValue":9,"cardValue":54},"33445566000JJJQQQKKK":{"cardType":11,"cardLength":4,"maxPokeValue":13,"minPokeValue":10,"cardValue":58},"33445577000JJJQQQKKK":{"cardType":11,"cardLength":4,"maxPokeValue":13,"minPokeValue":10,"cardValue":58},"33446677000JJJQQQKKK":{"cardType":11,"cardLength":4,"maxPokeValue":13,"minPokeValue":10,"cardValue":58},"33556677000JJJQQQKKK":{"cardType":11,"cardLength":4,"maxPokeValue":13,"minPokeValue":10,"cardValue":58},"44556677000JJJQQQKKK":{"cardType":11,"cardLength":4,"maxPokeValue":13,"minPokeValue":10,"cardValue":58},"33445588000JJJQQQKKK":{"cardType":11,"cardLength":4,"maxPokeValue":13,"minPokeValue":10,"cardValue":58},"33446688000JJJQQQKKK":{"cardType":11,"cardLength":4,"maxPokeValue":13,"minPokeValue":10,"cardValue":58},"33556688000JJJQQQKKK":{"cardType":11,"cardLength":4,"maxPokeValue":13,"minPokeValue":10,"cardValue":58},"44556688000JJJQQQKKK":{"cardType":11,"cardLength":4,"maxPokeValue":13,"minPokeValue":10,"cardValue":58},"33447788000JJJQQQKKK":{"cardType":11,"cardLength":4,"maxPokeValue":13,"minPokeValue":10,"cardValue":58},"33557788000JJJQQQKKK":{"cardType":11,"cardLength":4,"maxPokeValue":13,"minPokeValue":10,"cardValue":58},"44557788000JJJQQQKKK":{"cardType":11,"cardLength":4,"maxPokeValue":13,"minPokeValue":10,"cardValue":58},"33667788000JJJQQQKKK":{"cardType":11,"cardLength":4,"maxPokeValue":13,"minPokeValue":10,"cardValue":58},"44667788000JJJQQQKKK":{"cardType":11,"cardLength":4,"maxPokeValue":13,"minPokeValue":10,"cardValue":58},"55667788000JJJQQQKKK":{"cardType":11,"cardLength":4,"maxPokeValue":13,"minPokeValue":10,"cardValue":58},"33445599000JJJQQQKKK":{"cardType":11,"cardLength":4,"maxPokeValue":13,"minPokeValue":10,"cardValue":58},"33446699000JJJQQQKKK":{"cardType":11,"cardLength":4,"maxPokeValue":13,"minPokeValue":10,"cardValue":58},"33556699000JJJQQQKKK":{"cardType":11,"cardLength":4,"maxPokeValue":13,"minPokeValue":10,"cardValue":58},"44556699000JJJQQQKKK":{"cardType":11,"cardLength":4,"maxPokeValue":13,"minPokeValue":10,"cardValue":58},"33447799000JJJQQQKKK":{"cardType":11,"cardLength":4,"maxPokeValue":13,"minPokeValue":10,"cardValue":58},"33557799000JJJQQQKKK":{"cardType":11,"cardLength":4,"maxPokeValue":13,"minPokeValue":10,"cardValue":58},"44557799000JJJQQQKKK":{"cardType":11,"cardLength":4,"maxPokeValue":13,"minPokeValue":10,"cardValue":58},"33667799000JJJQQQKKK":{"cardType":11,"cardLength":4,"maxPokeValue":13,"minPokeValue":10,"cardValue":58},"44667799000JJJQQQKKK":{"cardType":11,"cardLength":4,"maxPokeValue":13,"minPokeValue":10,"cardValue":58},"55667799000JJJQQQKKK":{"cardType":11,"cardLength":4,"maxPokeValue":13,"minPokeValue":10,"cardValue":58},"33448899000JJJQQQKKK":{"cardType":11,"cardLength":4,"maxPokeValue":13,"minPokeValue":10,"cardValue":58},"33558899000JJJQQQKKK":{"cardType":11,"cardLength":4,"maxPokeValue":13,"minPokeValue":10,"cardValue":58},"44558899000JJJQQQKKK":{"cardType":11,"cardLength":4,"maxPokeValue":13,"minPokeValue":10,"cardValue":58},"33668899000JJJQQQKKK":{"cardType":11,"cardLength":4,"maxPokeValue":13,"minPokeValue":10,"cardValue":58},"44668899000JJJQQQKKK":{"cardType":11,"cardLength":4,"maxPokeValue":13,"minPokeValue":10,"cardValue":58},"55668899000JJJQQQKKK":{"cardType":11,"cardLength":4,"maxPokeValue":13,"minPokeValue":10,"cardValue":58},"33778899000JJJQQQKKK":{"cardType":11,"cardLength":4,"maxPokeValue":13,"minPokeValue":10,"cardValue":58},"44778899000JJJQQQKKK":{"cardType":11,"cardLength":4,"maxPokeValue":13,"minPokeValue":10,"cardValue":58},"55778899000JJJQQQKKK":{"cardType":11,"cardLength":4,"maxPokeValue":13,"minPokeValue":10,"cardValue":58},"66778899000JJJQQQKKK":{"cardType":11,"cardLength":4,"maxPokeValue":13,"minPokeValue":10,"cardValue":58},"334455000JJJQQQKKKAA":{"cardType":11,"cardLength":4,"maxPokeValue":13,"minPokeValue":10,"cardValue":58}}