{"367000JJJQQQKKKW":{"cardType":10,"cardLength":4,"maxPokeValue":13,"minPokeValue":10,"cardValue":58},"467000JJJQQQKKKW":{"cardType":10,"cardLength":4,"maxPokeValue":13,"minPokeValue":10,"cardValue":58},"567000JJJQQQKKKW":{"cardType":10,"cardLength":4,"maxPokeValue":13,"minPokeValue":10,"cardValue":58},"667000JJJQQQKKKW":{"cardType":10,"cardLength":4,"maxPokeValue":13,"minPokeValue":10,"cardValue":58},"377000JJJQQQKKKW":{"cardType":10,"cardLength":4,"maxPokeValue":13,"minPokeValue":10,"cardValue":58},"477000JJJQQQKKKW":{"cardType":10,"cardLength":4,"maxPokeValue":13,"minPokeValue":10,"cardValue":58},"577000JJJQQQKKKW":{"cardType":10,"cardLength":4,"maxPokeValue":13,"minPokeValue":10,"cardValue":58},"677000JJJQQQKKKW":{"cardType":10,"cardLength":4,"maxPokeValue":13,"minPokeValue":10,"cardValue":58},"777000JJJQQQKKKW":{"cardType":10,"cardLength":4,"maxPokeValue":13,"minPokeValue":10,"cardValue":68},"338000JJJQQQKKKW":{"cardType":10,"cardLength":4,"maxPokeValue":13,"minPokeValue":10,"cardValue":58},"348000JJJQQQKKKW":{"cardType":10,"cardLength":4,"maxPokeValue":13,"minPokeValue":10,"cardValue":58},"448000JJJQQQKKKW":{"cardType":10,"cardLength":4,"maxPokeValue":13,"minPokeValue":10,"cardValue":58},"358000JJJQQQKKKW":{"cardType":10,"cardLength":4,"maxPokeValue":13,"minPokeValue":10,"cardValue":58},"458000JJJQQQKKKW":{"cardType":10,"cardLength":4,"maxPokeValue":13,"minPokeValue":10,"cardValue":58},"558000JJJQQQKKKW":{"cardType":10,"cardLength":4,"maxPokeValue":13,"minPokeValue":10,"cardValue":58},"368000JJJQQQKKKW":{"cardType":10,"cardLength":4,"maxPokeValue":13,"minPokeValue":10,"cardValue":58},"468000JJJQQQKKKW":{"cardType":10,"cardLength":4,"maxPokeValue":13,"minPokeValue":10,"cardValue":58},"568000JJJQQQKKKW":{"cardType":10,"cardLength":4,"maxPokeValue":13,"minPokeValue":10,"cardValue":58},"668000JJJQQQKKKW":{"cardType":10,"cardLength":4,"maxPokeValue":13,"minPokeValue":10,"cardValue":58},"378000JJJQQQKKKW":{"cardType":10,"cardLength":4,"maxPokeValue":13,"minPokeValue":10,"cardValue":58},"478000JJJQQQKKKW":{"cardType":10,"cardLength":4,"maxPokeValue":13,"minPokeValue":10,"cardValue":58},"578000JJJQQQKKKW":{"cardType":10,"cardLength":4,"maxPokeValue":13,"minPokeValue":10,"cardValue":58},"678000JJJQQQKKKW":{"cardType":10,"cardLength":4,"maxPokeValue":13,"minPokeValue":10,"cardValue":58},"778000JJJQQQKKKW":{"cardType":10,"cardLength":4,"maxPokeValue":13,"minPokeValue":10,"cardValue":58},"388000JJJQQQKKKW":{"cardType":10,"cardLength":4,"maxPokeValue":13,"minPokeValue":10,"cardValue":58},"488000JJJQQQKKKW":{"cardType":10,"cardLength":4,"maxPokeValue":13,"minPokeValue":10,"cardValue":58},"588000JJJQQQKKKW":{"cardType":10,"cardLength":4,"maxPokeValue":13,"minPokeValue":10,"cardValue":58},"688000JJJQQQKKKW":{"cardType":10,"cardLength":4,"maxPokeValue":13,"minPokeValue":10,"cardValue":58},"788000JJJQQQKKKW":{"cardType":10,"cardLength":4,"maxPokeValue":13,"minPokeValue":10,"cardValue":58},"888000JJJQQQKKKW":{"cardType":10,"cardLength":4,"maxPokeValue":13,"minPokeValue":10,"cardValue":69},"339000JJJQQQKKKW":{"cardType":10,"cardLength":4,"maxPokeValue":13,"minPokeValue":10,"cardValue":58},"349000JJJQQQKKKW":{"cardType":10,"cardLength":4,"maxPokeValue":13,"minPokeValue":10,"cardValue":58},"449000JJJQQQKKKW":{"cardType":10,"cardLength":4,"maxPokeValue":13,"minPokeValue":10,"cardValue":58},"359000JJJQQQKKKW":{"cardType":10,"cardLength":4,"maxPokeValue":13,"minPokeValue":10,"cardValue":58},"459000JJJQQQKKKW":{"cardType":10,"cardLength":4,"maxPokeValue":13,"minPokeValue":10,"cardValue":58},"559000JJJQQQKKKW":{"cardType":10,"cardLength":4,"maxPokeValue":13,"minPokeValue":10,"cardValue":58},"369000JJJQQQKKKW":{"cardType":10,"cardLength":4,"maxPokeValue":13,"minPokeValue":10,"cardValue":58},"469000JJJQQQKKKW":{"cardType":10,"cardLength":4,"maxPokeValue":13,"minPokeValue":10,"cardValue":58},"569000JJJQQQKKKW":{"cardType":10,"cardLength":4,"maxPokeValue":13,"minPokeValue":10,"cardValue":58},"669000JJJQQQKKKW":{"cardType":10,"cardLength":4,"maxPokeValue":13,"minPokeValue":10,"cardValue":58},"379000JJJQQQKKKW":{"cardType":10,"cardLength":4,"maxPokeValue":13,"minPokeValue":10,"cardValue":58},"479000JJJQQQKKKW":{"cardType":10,"cardLength":4,"maxPokeValue":13,"minPokeValue":10,"cardValue":58},"579000JJJQQQKKKW":{"cardType":10,"cardLength":4,"maxPokeValue":13,"minPokeValue":10,"cardValue":58},"679000JJJQQQKKKW":{"cardType":10,"cardLength":4,"maxPokeValue":13,"minPokeValue":10,"cardValue":58},"779000JJJQQQKKKW":{"cardType":10,"cardLength":4,"maxPokeValue":13,"minPokeValue":10,"cardValue":58},"389000JJJQQQKKKW":{"cardType":10,"cardLength":4,"maxPokeValue":13,"minPokeValue":10,"cardValue":58},"489000JJJQQQKKKW":{"cardType":10,"cardLength":4,"maxPokeValue":13,"minPokeValue":10,"cardValue":58},"589000JJJQQQKKKW":{"cardType":10,"cardLength":4,"maxPokeValue":13,"minPokeValue":10,"cardValue":58},"689000JJJQQQKKKW":{"cardType":10,"cardLength":4,"maxPokeValue":13,"minPokeValue":10,"cardValue":58},"789000JJJQQQKKKW":{"cardType":10,"cardLength":4,"maxPokeValue":13,"minPokeValue":10,"cardValue":58},"889000JJJQQQKKKW":{"cardType":10,"cardLength":4,"maxPokeValue":13,"minPokeValue":10,"cardValue":58},"399000JJJQQQKKKW":{"cardType":10,"cardLength":4,"maxPokeValue":13,"minPokeValue":10,"cardValue":58},"499000JJJQQQKKKW":{"cardType":10,"cardLength":4,"maxPokeValue":13,"minPokeValue":10,"cardValue":58},"599000JJJQQQKKKW":{"cardType":10,"cardLength":4,"maxPokeValue":13,"minPokeValue":10,"cardValue":58},"699000JJJQQQKKKW":{"cardType":10,"cardLength":4,"maxPokeValue":13,"minPokeValue":10,"cardValue":58},"799000JJJQQQKKKW":{"cardType":10,"cardLength":4,"maxPokeValue":13,"minPokeValue":10,"cardValue":58},"899000JJJQQQKKKW":{"cardType":10,"cardLength":4,"maxPokeValue":13,"minPokeValue":10,"cardValue":58},"33000JJJQQQKKKAW":{"cardType":10,"cardLength":4,"maxPokeValue":13,"minPokeValue":10,"cardValue":58},"34000JJJQQQKKKAW":{"cardType":10,"cardLength":4,"maxPokeValue":13,"minPokeValue":10,"cardValue":58},"44000JJJQQQKKKAW":{"cardType":10,"cardLength":4,"maxPokeValue":13,"minPokeValue":10,"cardValue":58},"35000JJJQQQKKKAW":{"cardType":10,"cardLength":4,"maxPokeValue":13,"minPokeValue":10,"cardValue":58},"45000JJJQQQKKKAW":{"cardType":10,"cardLength":4,"maxPokeValue":13,"minPokeValue":10,"cardValue":58},"55000JJJQQQKKKAW":{"cardType":10,"cardLength":4,"maxPokeValue":13,"minPokeValue":10,"cardValue":58},"36000JJJQQQKKKAW":{"cardType":10,"cardLength":4,"maxPokeValue":13,"minPokeValue":10,"cardValue":58},"46000JJJQQQKKKAW":{"cardType":10,"cardLength":4,"maxPokeValue":13,"minPokeValue":10,"cardValue":58},"56000JJJQQQKKKAW":{"cardType":10,"cardLength":4,"maxPokeValue":13,"minPokeValue":10,"cardValue":58},"66000JJJQQQKKKAW":{"cardType":10,"cardLength":4,"maxPokeValue":13,"minPokeValue":10,"cardValue":58},"37000JJJQQQKKKAW":{"cardType":10,"cardLength":4,"maxPokeValue":13,"minPokeValue":10,"cardValue":58},"47000JJJQQQKKKAW":{"cardType":10,"cardLength":4,"maxPokeValue":13,"minPokeValue":10,"cardValue":58},"57000JJJQQQKKKAW":{"cardType":10,"cardLength":4,"maxPokeValue":13,"minPokeValue":10,"cardValue":58},"67000JJJQQQKKKAW":{"cardType":10,"cardLength":4,"maxPokeValue":13,"minPokeValue":10,"cardValue":58},"77000JJJQQQKKKAW":{"cardType":10,"cardLength":4,"maxPokeValue":13,"minPokeValue":10,"cardValue":58},"38000JJJQQQKKKAW":{"cardType":10,"cardLength":4,"maxPokeValue":13,"minPokeValue":10,"cardValue":58},"48000JJJQQQKKKAW":{"cardType":10,"cardLength":4,"maxPokeValue":13,"minPokeValue":10,"cardValue":58},"58000JJJQQQKKKAW":{"cardType":10,"cardLength":4,"maxPokeValue":13,"minPokeValue":10,"cardValue":58},"68000JJJQQQKKKAW":{"cardType":10,"cardLength":4,"maxPokeValue":13,"minPokeValue":10,"cardValue":58},"78000JJJQQQKKKAW":{"cardType":10,"cardLength":4,"maxPokeValue":13,"minPokeValue":10,"cardValue":58},"88000JJJQQQKKKAW":{"cardType":10,"cardLength":4,"maxPokeValue":13,"minPokeValue":10,"cardValue":58},"39000JJJQQQKKKAW":{"cardType":10,"cardLength":4,"maxPokeValue":13,"minPokeValue":10,"cardValue":58},"49000JJJQQQKKKAW":{"cardType":10,"cardLength":4,"maxPokeValue":13,"minPokeValue":10,"cardValue":58},"59000JJJQQQKKKAW":{"cardType":10,"cardLength":4,"maxPokeValue":13,"minPokeValue":10,"cardValue":58},"69000JJJQQQKKKAW":{"cardType":10,"cardLength":4,"maxPokeValue":13,"minPokeValue":10,"cardValue":58},"79000JJJQQQKKKAW":{"cardType":10,"cardLength":4,"maxPokeValue":13,"minPokeValue":10,"cardValue":58},"89000JJJQQQKKKAW":{"cardType":10,"cardLength":4,"maxPokeValue":13,"minPokeValue":10,"cardValue":58},"99000JJJQQQKKKAW":{"cardType":10,"cardLength":4,"maxPokeValue":13,"minPokeValue":10,"cardValue":58},"3000JJJQQQKKKAAW":{"cardType":10,"cardLength":4,"maxPokeValue":13,"minPokeValue":10,"cardValue":58},"4000JJJQQQKKKAAW":{"cardType":10,"cardLength":4,"maxPokeValue":13,"minPokeValue":10,"cardValue":58},"5000JJJQQQKKKAAW":{"cardType":10,"cardLength":4,"maxPokeValue":13,"minPokeValue":10,"cardValue":58},"6000JJJQQQKKKAAW":{"cardType":10,"cardLength":4,"maxPokeValue":13,"minPokeValue":10,"cardValue":58},"7000JJJQQQKKKAAW":{"cardType":10,"cardLength":4,"maxPokeValue":13,"minPokeValue":10,"cardValue":58},"8000JJJQQQKKKAAW":{"cardType":10,"cardLength":4,"maxPokeValue":13,"minPokeValue":10,"cardValue":58},"9000JJJQQQKKKAAW":{"cardType":10,"cardLength":4,"maxPokeValue":13,"minPokeValue":10,"cardValue":58},"000JJJQQQKKKAAAW":{"cardType":10,"cardLength":4,"maxPokeValue":14,"minPokeValue":11,"cardValue":75},"33000JJJQQQKKK2W":{"cardType":10,"cardLength":4,"maxPokeValue":13,"minPokeValue":10,"cardValue":58},"34000JJJQQQKKK2W":{"cardType":10,"cardLength":4,"maxPokeValue":13,"minPokeValue":10,"cardValue":58},"44000JJJQQQKKK2W":{"cardType":10,"cardLength":4,"maxPokeValue":13,"minPokeValue":10,"cardValue":58},"35000JJJQQQKKK2W":{"cardType":10,"cardLength":4,"maxPokeValue":13,"minPokeValue":10,"cardValue":58},"45000JJJQQQKKK2W":{"cardType":10,"cardLength":4,"maxPokeValue":13,"minPokeValue":10,"cardValue":58},"55000JJJQQQKKK2W":{"cardType":10,"cardLength":4,"maxPokeValue":13,"minPokeValue":10,"cardValue":58},"36000JJJQQQKKK2W":{"cardType":10,"cardLength":4,"maxPokeValue":13,"minPokeValue":10,"cardValue":58}}