{"33344455588J":{"cardType":10,"cardLength":3,"maxPokeValue":5,"minPokeValue":3,"cardValue":21},"33344455569J":{"cardType":10,"cardLength":3,"maxPokeValue":5,"minPokeValue":3,"cardValue":21},"33344455579J":{"cardType":10,"cardLength":3,"maxPokeValue":5,"minPokeValue":3,"cardValue":21},"33344455589J":{"cardType":10,"cardLength":3,"maxPokeValue":5,"minPokeValue":3,"cardValue":21},"33344455599J":{"cardType":10,"cardLength":3,"maxPokeValue":5,"minPokeValue":3,"cardValue":21},"33344455560J":{"cardType":10,"cardLength":3,"maxPokeValue":5,"minPokeValue":3,"cardValue":21},"33344455570J":{"cardType":10,"cardLength":3,"maxPokeValue":5,"minPokeValue":3,"cardValue":21},"33344455580J":{"cardType":10,"cardLength":3,"maxPokeValue":5,"minPokeValue":3,"cardValue":21},"33344455590J":{"cardType":10,"cardLength":3,"maxPokeValue":5,"minPokeValue":3,"cardValue":21},"33344455500J":{"cardType":10,"cardLength":3,"maxPokeValue":5,"minPokeValue":3,"cardValue":21},"3334445556JJ":{"cardType":10,"cardLength":3,"maxPokeValue":5,"minPokeValue":3,"cardValue":21},"3334445557JJ":{"cardType":10,"cardLength":3,"maxPokeValue":5,"minPokeValue":3,"cardValue":21},"3334445558JJ":{"cardType":10,"cardLength":3,"maxPokeValue":5,"minPokeValue":3,"cardValue":21},"3334445559JJ":{"cardType":10,"cardLength":3,"maxPokeValue":5,"minPokeValue":3,"cardValue":21},"3334445550JJ":{"cardType":10,"cardLength":3,"maxPokeValue":5,"minPokeValue":3,"cardValue":21},"33344455566Q":{"cardType":10,"cardLength":3,"maxPokeValue":5,"minPokeValue":3,"cardValue":21},"33344455567Q":{"cardType":10,"cardLength":3,"maxPokeValue":5,"minPokeValue":3,"cardValue":21},"33344455577Q":{"cardType":10,"cardLength":3,"maxPokeValue":5,"minPokeValue":3,"cardValue":21},"33344455568Q":{"cardType":10,"cardLength":3,"maxPokeValue":5,"minPokeValue":3,"cardValue":21},"33344455578Q":{"cardType":10,"cardLength":3,"maxPokeValue":5,"minPokeValue":3,"cardValue":21},"33344455588Q":{"cardType":10,"cardLength":3,"maxPokeValue":5,"minPokeValue":3,"cardValue":21},"33344455569Q":{"cardType":10,"cardLength":3,"maxPokeValue":5,"minPokeValue":3,"cardValue":21},"33344455579Q":{"cardType":10,"cardLength":3,"maxPokeValue":5,"minPokeValue":3,"cardValue":21},"33344455589Q":{"cardType":10,"cardLength":3,"maxPokeValue":5,"minPokeValue":3,"cardValue":21},"33344455599Q":{"cardType":10,"cardLength":3,"maxPokeValue":5,"minPokeValue":3,"cardValue":21},"33344455560Q":{"cardType":10,"cardLength":3,"maxPokeValue":5,"minPokeValue":3,"cardValue":21},"33344455570Q":{"cardType":10,"cardLength":3,"maxPokeValue":5,"minPokeValue":3,"cardValue":21},"33344455580Q":{"cardType":10,"cardLength":3,"maxPokeValue":5,"minPokeValue":3,"cardValue":21},"33344455590Q":{"cardType":10,"cardLength":3,"maxPokeValue":5,"minPokeValue":3,"cardValue":21},"33344455500Q":{"cardType":10,"cardLength":3,"maxPokeValue":5,"minPokeValue":3,"cardValue":21},"3334445556JQ":{"cardType":10,"cardLength":3,"maxPokeValue":5,"minPokeValue":3,"cardValue":21},"3334445557JQ":{"cardType":10,"cardLength":3,"maxPokeValue":5,"minPokeValue":3,"cardValue":21},"3334445558JQ":{"cardType":10,"cardLength":3,"maxPokeValue":5,"minPokeValue":3,"cardValue":21},"3334445559JQ":{"cardType":10,"cardLength":3,"maxPokeValue":5,"minPokeValue":3,"cardValue":21},"3334445550JQ":{"cardType":10,"cardLength":3,"maxPokeValue":5,"minPokeValue":3,"cardValue":21},"333444555JJQ":{"cardType":10,"cardLength":3,"maxPokeValue":5,"minPokeValue":3,"cardValue":21},"3334445556QQ":{"cardType":10,"cardLength":3,"maxPokeValue":5,"minPokeValue":3,"cardValue":21},"3334445557QQ":{"cardType":10,"cardLength":3,"maxPokeValue":5,"minPokeValue":3,"cardValue":21},"3334445558QQ":{"cardType":10,"cardLength":3,"maxPokeValue":5,"minPokeValue":3,"cardValue":21},"3334445559QQ":{"cardType":10,"cardLength":3,"maxPokeValue":5,"minPokeValue":3,"cardValue":21},"3334445550QQ":{"cardType":10,"cardLength":3,"maxPokeValue":5,"minPokeValue":3,"cardValue":21},"333444555JQQ":{"cardType":10,"cardLength":3,"maxPokeValue":5,"minPokeValue":3,"cardValue":21},"33344455566K":{"cardType":10,"cardLength":3,"maxPokeValue":5,"minPokeValue":3,"cardValue":21},"33344455567K":{"cardType":10,"cardLength":3,"maxPokeValue":5,"minPokeValue":3,"cardValue":21},"33344455577K":{"cardType":10,"cardLength":3,"maxPokeValue":5,"minPokeValue":3,"cardValue":21},"33344455568K":{"cardType":10,"cardLength":3,"maxPokeValue":5,"minPokeValue":3,"cardValue":21},"33344455578K":{"cardType":10,"cardLength":3,"maxPokeValue":5,"minPokeValue":3,"cardValue":21},"33344455588K":{"cardType":10,"cardLength":3,"maxPokeValue":5,"minPokeValue":3,"cardValue":21},"33344455569K":{"cardType":10,"cardLength":3,"maxPokeValue":5,"minPokeValue":3,"cardValue":21},"33344455579K":{"cardType":10,"cardLength":3,"maxPokeValue":5,"minPokeValue":3,"cardValue":21},"33344455589K":{"cardType":10,"cardLength":3,"maxPokeValue":5,"minPokeValue":3,"cardValue":21},"33344455599K":{"cardType":10,"cardLength":3,"maxPokeValue":5,"minPokeValue":3,"cardValue":21},"33344455560K":{"cardType":10,"cardLength":3,"maxPokeValue":5,"minPokeValue":3,"cardValue":21},"33344455570K":{"cardType":10,"cardLength":3,"maxPokeValue":5,"minPokeValue":3,"cardValue":21},"33344455580K":{"cardType":10,"cardLength":3,"maxPokeValue":5,"minPokeValue":3,"cardValue":21},"33344455590K":{"cardType":10,"cardLength":3,"maxPokeValue":5,"minPokeValue":3,"cardValue":21},"33344455500K":{"cardType":10,"cardLength":3,"maxPokeValue":5,"minPokeValue":3,"cardValue":21},"3334445556JK":{"cardType":10,"cardLength":3,"maxPokeValue":5,"minPokeValue":3,"cardValue":21},"3334445557JK":{"cardType":10,"cardLength":3,"maxPokeValue":5,"minPokeValue":3,"cardValue":21},"3334445558JK":{"cardType":10,"cardLength":3,"maxPokeValue":5,"minPokeValue":3,"cardValue":21},"3334445559JK":{"cardType":10,"cardLength":3,"maxPokeValue":5,"minPokeValue":3,"cardValue":21},"3334445550JK":{"cardType":10,"cardLength":3,"maxPokeValue":5,"minPokeValue":3,"cardValue":21},"333444555JJK":{"cardType":10,"cardLength":3,"maxPokeValue":5,"minPokeValue":3,"cardValue":21},"3334445556QK":{"cardType":10,"cardLength":3,"maxPokeValue":5,"minPokeValue":3,"cardValue":21},"3334445557QK":{"cardType":10,"cardLength":3,"maxPokeValue":5,"minPokeValue":3,"cardValue":21},"3334445558QK":{"cardType":10,"cardLength":3,"maxPokeValue":5,"minPokeValue":3,"cardValue":21},"3334445559QK":{"cardType":10,"cardLength":3,"maxPokeValue":5,"minPokeValue":3,"cardValue":21},"3334445550QK":{"cardType":10,"cardLength":3,"maxPokeValue":5,"minPokeValue":3,"cardValue":21},"333444555JQK":{"cardType":10,"cardLength":3,"maxPokeValue":5,"minPokeValue":3,"cardValue":21},"333444555QQK":{"cardType":10,"cardLength":3,"maxPokeValue":5,"minPokeValue":3,"cardValue":21},"3334445556KK":{"cardType":10,"cardLength":3,"maxPokeValue":5,"minPokeValue":3,"cardValue":21},"3334445557KK":{"cardType":10,"cardLength":3,"maxPokeValue":5,"minPokeValue":3,"cardValue":21},"3334445558KK":{"cardType":10,"cardLength":3,"maxPokeValue":5,"minPokeValue":3,"cardValue":21},"3334445559KK":{"cardType":10,"cardLength":3,"maxPokeValue":5,"minPokeValue":3,"cardValue":21},"3334445550KK":{"cardType":10,"cardLength":3,"maxPokeValue":5,"minPokeValue":3,"cardValue":21},"333444555JKK":{"cardType":10,"cardLength":3,"maxPokeValue":5,"minPokeValue":3,"cardValue":21},"333444555QKK":{"cardType":10,"cardLength":3,"maxPokeValue":5,"minPokeValue":3,"cardValue":21},"33344455566A":{"cardType":10,"cardLength":3,"maxPokeValue":5,"minPokeValue":3,"cardValue":21},"33344455567A":{"cardType":10,"cardLength":3,"maxPokeValue":5,"minPokeValue":3,"cardValue":21},"33344455577A":{"cardType":10,"cardLength":3,"maxPokeValue":5,"minPokeValue":3,"cardValue":21},"33344455568A":{"cardType":10,"cardLength":3,"maxPokeValue":5,"minPokeValue":3,"cardValue":21},"33344455578A":{"cardType":10,"cardLength":3,"maxPokeValue":5,"minPokeValue":3,"cardValue":21},"33344455588A":{"cardType":10,"cardLength":3,"maxPokeValue":5,"minPokeValue":3,"cardValue":21},"33344455569A":{"cardType":10,"cardLength":3,"maxPokeValue":5,"minPokeValue":3,"cardValue":21},"33344455579A":{"cardType":10,"cardLength":3,"maxPokeValue":5,"minPokeValue":3,"cardValue":21},"33344455589A":{"cardType":10,"cardLength":3,"maxPokeValue":5,"minPokeValue":3,"cardValue":21},"33344455599A":{"cardType":10,"cardLength":3,"maxPokeValue":5,"minPokeValue":3,"cardValue":21},"33344455560A":{"cardType":10,"cardLength":3,"maxPokeValue":5,"minPokeValue":3,"cardValue":21},"33344455570A":{"cardType":10,"cardLength":3,"maxPokeValue":5,"minPokeValue":3,"cardValue":21},"33344455580A":{"cardType":10,"cardLength":3,"maxPokeValue":5,"minPokeValue":3,"cardValue":21},"33344455590A":{"cardType":10,"cardLength":3,"maxPokeValue":5,"minPokeValue":3,"cardValue":21},"33344455500A":{"cardType":10,"cardLength":3,"maxPokeValue":5,"minPokeValue":3,"cardValue":21},"3334445556JA":{"cardType":10,"cardLength":3,"maxPokeValue":5,"minPokeValue":3,"cardValue":21},"3334445557JA":{"cardType":10,"cardLength":3,"maxPokeValue":5,"minPokeValue":3,"cardValue":21},"3334445558JA":{"cardType":10,"cardLength":3,"maxPokeValue":5,"minPokeValue":3,"cardValue":21},"3334445559JA":{"cardType":10,"cardLength":3,"maxPokeValue":5,"minPokeValue":3,"cardValue":21},"3334445550JA":{"cardType":10,"cardLength":3,"maxPokeValue":5,"minPokeValue":3,"cardValue":21},"333444555JJA":{"cardType":10,"cardLength":3,"maxPokeValue":5,"minPokeValue":3,"cardValue":21},"3334445556QA":{"cardType":10,"cardLength":3,"maxPokeValue":5,"minPokeValue":3,"cardValue":21},"3334445557QA":{"cardType":10,"cardLength":3,"maxPokeValue":5,"minPokeValue":3,"cardValue":21}}